Figure_1.png
LICENSE
README.md
pyproject.toml
setup.py
src/cfmdarts/__init__.py
src/cfmdarts/cfmdarts.py
src/cfmdarts.egg-info/PKG-INFO
src/cfmdarts.egg-info/SOURCES.txt
src/cfmdarts.egg-info/dependency_links.txt
src/cfmdarts.egg-info/top_level.txt
test/test_cfmdarts.py