Metadata-Version: 2.1
Name: cfmdarts
Version: 0.1.4
Summary: cfmdarts is a Python library that simulates the projectile motion of darts.
Home-page: https://github.com/Araphor0/cfmdarts
Author: Matthew Squire, Luke Sargent, Cameron Trew, Aron Russell
License: UNKNOWN
Platform: UNKNOWN
Classifier: Programming Language :: Python :: 3
Classifier: License :: OSI Approved :: MIT License
Classifier: Operating System :: OS Independent
Requires-Python: >=3.6
License-File: LICENSE
